fafnir.py
fafnir-0.1.2.dist-info/LICENSE
fafnir-0.1.2.dist-info/METADATA
fafnir-0.1.2.dist-info/WHEEL
fafnir-0.1.2.dist-info/entry_points.txt
fafnir-0.1.2.dist-info/top_level.txt
fafnir-0.1.2.dist-info/RECORD
